{"animations":{"idle-1":{"framerate":24,"loop":false,"name":"idle-1","offset":{"x":-362,"y":-645},"play_next":"","prefix":"GF Dancing Beat0","reset_at_beat":true},"idle-2":{"framerate":24,"loop":false,"name":"idle-2","offset":{"x":-363.117737,"y":-645.000183},"play_next":"","prefix":"GF Dancing Beat2 0","reset_at_beat":true},"sing-down":{"framerate":24,"loop":false,"name":"sing-down","offset":{"x":-362,"y":-634},"play_next":"idle-1","prefix":"GF Down Note0","reset_at_beat":false},"sing-left":{"framerate":24,"loop":false,"name":"sing-left","offset":{"x":-362,"y":-635},"play_next":"idle-1","prefix":"GF left note0","reset_at_beat":false},"sing-right":{"framerate":24,"loop":false,"name":"sing-right","offset":{"x":-362,"y":-635},"play_next":"idle-1","prefix":"GF Right Note0","reset_at_beat":false},"sing-up":{"framerate":24,"loop":false,"name":"sing-up","offset":{"x":-362,"y":-658},"play_next":"idle-1","prefix":"GF Up Note0","reset_at_beat":false},"taunt-cheer":{"framerate":24,"loop":false,"name":"taunt-cheer","offset":{"x":-362,"y":-654},"play_next":"idle-1","prefix":"GF Cheer0","reset_at_beat":false}},"autoplay":"idle-1","camera_offset":{"x":0,"y":-240},"flip":false,"hp_color":"a5004d","icon":"gf","imageatlas":"actors/girlfriend","name":"gf","sing_len":3}